omni/__init__.py
omni_binding_api-0.0.2.dist-info/LICENSE
omni_binding_api-0.0.2.dist-info/METADATA
omni_binding_api-0.0.2.dist-info/WHEEL
omni_binding_api-0.0.2.dist-info/top_level.txt
omni_binding_api-0.0.2.dist-info/RECORD
