Metadata-Version: 2.1
Name: omni-binding-api
Version: 0.0.2
Summary: LLM-powered omni api
Author-email: Harrison Green <harrisonmichaelgreen@gmail.com>
Project-URL: Homepage, https://github.com/hgarrereyn/omni
Project-URL: Issues, https://github.com/hgarrereyn/omni/issues
Classifier: Programming Language :: Python :: 3
Classifier: License :: OSI Approved :: MIT License
Classifier: Operating System :: OS Independent
Requires-Python: >=3.8
License-File: LICENSE
Requires-Dist: litellm>=1.53.1
